LICENSE.md
README.md
setup.cfg
setup.py
MultifunctionTools/__init__.py
MultifunctionTools.egg-info/PKG-INFO
MultifunctionTools.egg-info/SOURCES.txt
MultifunctionTools.egg-info/dependency_links.txt
MultifunctionTools.egg-info/requires.txt
MultifunctionTools.egg-info/top_level.txt
MultifunctionTools/Cipher/__AdvancedCiphering.py
MultifunctionTools/Cipher/__BasicCiphering.py
MultifunctionTools/Cipher/__CipherAlgos.py
MultifunctionTools/Cipher/__init__.py
MultifunctionTools/Convert/__convertImage.py
MultifunctionTools/Convert/__convertType.py
MultifunctionTools/Convert/__init__.py
MultifunctionTools/Exceptions/__init__.py
MultifunctionTools/Hash/__AdvancedHashing.py
MultifunctionTools/Hash/__BasicHashing.py
MultifunctionTools/Hash/__HashAlgos.py
MultifunctionTools/Hash/__init__.py