Metadata-Version: 2.1
Name: MultifunctionTools
Version: 1.0.0b8
Summary: The MultifunctionTools library is a comprehensive collection of handy utilities and tools designed to enhance your Python coding experience.
Home-page: https://github.com/veHRz/MultifunctionTools
Download-URL: https://github.com/veHRz/MultifunctionTools/archive/refs/tags/1.0.0b8.tar.gz
Author: veHRz
Author-email: vehrzyt@gmail.com
License: MIT
Keywords: TOOLS,CIPHER,HASH,CONVERT,MULTI-USAGE,MULTI
Classifier: Development Status :: 4 - Beta
Classifier: Intended Audience :: Developers
Classifier: Topic :: Software Development :: Build Tools
Classifier: Topic :: Security
Classifier: Topic :: Security :: Cryptography
Classifier: Topic :: Software Development :: Libraries :: Python Modules
Classifier: Topic :: Utilities
Classifier: Topic :: Other/Nonlisted Topic
Classifier: License :: OSI Approved :: MIT License
Classifier: Natural Language :: English
Classifier: Operating System :: Microsoft :: Windows
Classifier: Programming Language :: Python :: 3 :: Only
Classifier: Programming Language :: Python :: 3.9
Classifier: Programming Language :: Python :: 3.10
Classifier: Programming Language :: Python :: 3.11
Classifier: Programming Language :: Python :: 3.12
Classifier: Programming Language :: Python :: 3.13
License-File: LICENSE.md
